[{"image_name": "\\\\storage1.ris.wustl.edu\\wucci\\Active\\Merlin\\Morgan Lab\\MasterRaw\\KxR_1A\\Copy of Raws\\w8\\w8_2_Sec006_Montage\\Tile_r3-c2_w8_2_sec006_20220722T183910.tif", "y": "0", "x": "0", "quality_score": "[0.3091859]"}, {"image_name": "\\\\storage1.ris.wustl.edu\\wucci\\Active\\Merlin\\Morgan Lab\\MasterRaw\\KxR_1A\\Copy of Raws\\w8\\w8_2_Sec006_Montage\\Tile_r3-c2_w8_2_sec006_20220722T183910.tif", "y": "0", "x": "10240", "quality_score": "[0.50859123]"}, {"image_name": "\\\\storage1.ris.wustl.edu\\wucci\\Active\\Merlin\\Morgan Lab\\MasterRaw\\KxR_1A\\Copy of Raws\\w8\\w8_2_Sec006_Montage\\Tile_r3-c2_w8_2_sec006_20220722T183910.tif", "y": "10240", "x": "0", "quality_score": "[0.509371]"}, {"image_name": "\\\\storage1.ris.wustl.edu\\wucci\\Active\\Merlin\\Morgan Lab\\MasterRaw\\KxR_1A\\Copy of Raws\\w8\\w8_2_Sec006_Montage\\Tile_r3-c2_w8_2_sec006_20220722T183910.tif", "y": "10240", "x": "10240", "quality_score": "[0.44699782]"}, {"image_name": "\\\\storage1.ris.wustl.edu\\wucci\\Active\\Merlin\\Morgan Lab\\MasterRaw\\KxR_1A\\Copy of Raws\\w8\\w8_2_Sec006_Montage\\Tile_r3-c1_w8_2_sec006_20221219T140730.tif", "y": "0", "x": "0", "quality_score": "[0.5146803]"}, {"image_name": "\\\\storage1.ris.wustl.edu\\wucci\\Active\\Merlin\\Morgan Lab\\MasterRaw\\KxR_1A\\Copy of Raws\\w8\\w8_2_Sec006_Montage\\Tile_r3-c1_w8_2_sec006_20221219T140730.tif", "y": "0", "x": "10240", "quality_score": "[0.29741997]"}, {"image_name": "\\\\storage1.ris.wustl.edu\\wucci\\Active\\Merlin\\Morgan Lab\\MasterRaw\\KxR_1A\\Copy of Raws\\w8\\w8_2_Sec006_Montage\\Tile_r3-c1_w8_2_sec006_20221219T140730.tif", "y": "10240", "x": "0", "quality_score": "[0.5146547]"}, {"image_name": "\\\\storage1.ris.wustl.edu\\wucci\\Active\\Merlin\\Morgan Lab\\MasterRaw\\KxR_1A\\Copy of Raws\\w8\\w8_2_Sec006_Montage\\Tile_r3-c1_w8_2_sec006_20221219T140730.tif", "y": "10240", "x": "10240", "quality_score": "[0.36321354]"}]